[
  {
    "year": "99",
    "number": 90,
    "name": "지원자"
  },
  {
    "year": "99",
    "number": 91,
    "name": "지원자"
  },
  {
    "year": "73",
    "number": 10,
    "name": "김정표"
  },
  {
    "year": "84",
    "number": 30,
    "name": "최현석"
  },
  {
    "year": "85",
    "number": 9,
    "name": "전인정"
  },
  {
    "year": "86",
    "number": 11,
    "name": "김성일"
  },
  {
    "year": "86",
    "number": 28,
    "name": "조용일"
  },
  {
    "year": "87",
    "number": 33,
    "name": "강병용"
  },
  {
    "year": "87",
    "number": 20,
    "name": "박준우"
  },
  {
    "year": "87",
    "number": 17,
    "name": "양성호"
  },
  {
    "year": "87",
    "number": 19,
    "name": "홍승우"
  },
  {
    "year": "89",
    "number": 8,
    "name": "김동수"
  },
  {
    "year": "89",
    "number": 0,
    "name": "박준범"
  },
  {
    "year": "89",
    "number": 1,
    "name": "윤용준"
  },
  {
    "year": "89",
    "number": 4,
    "name": "이원식"
  },
  {
    "year": "89",
    "number": 12,
    "name": "이한별"
  },
  {
    "year": "89",
    "number": 22,
    "name": "임은철"
  },
  {
    "year": "89",
    "number": 31,
    "name": "장세원"
  },
  {
    "year": "89",
    "number": 42,
    "name": "최승빈"
  },
  {
    "year": "89",
    "number": 7,
    "name": "이원재"
  },
  {
    "year": "90",
    "number": 5,
    "name": "박치환"
  },
  {
    "year": "90",
    "number": 13,
    "name": "이민수"
  },
  {
    "year": "90",
    "number": 24,
    "name": "임시현"
  },
  {
    "year": "91",
    "number": 6,
    "name": "김백상"
  },
  {
    "year": "91",
    "number": 0,
    "name": "김혁준"
  },
  {
    "year": "93",
    "number": 0,
    "name": "황윤하"
  }
]
